LICENSE
README.md
setup.py
bin/calculate_pastro_fgmc
bin/calculate_pastro_fgmc_test_inj
bin/calculate_rates
bin/initialize_pastro_fgmc_model
bin/pastro_bg_dist_from_gstlal
bin/pastro_build_gstlal_model
bin/pastro_calculate_VT
bin/pastro_count_coinc
bin/pastro_inj_dist_from_gstlal
bin/pastro_plot_p_lr
bin/pastro_prepare_config
bin/pastro_set_lthresh_from_bg_gstlal
bin/pastro_test_model
gwsci_pastro.egg-info/PKG-INFO
gwsci_pastro.egg-info/SOURCES.txt
gwsci_pastro.egg-info/dependency_links.txt
gwsci_pastro.egg-info/top_level.txt
pastro/pastro.py