Metadata-Version: 2.1
Name: gwsci-pastro
Version: 1.0.0
Summary: Tools for calculating astrophysical probability of GW events
Home-page: https://git.ligo.org/gstlal/pastro
Author: Chad Hanna, Victoria Niu, Leo Tsukada, Anarya Ray
Author-email: chad.hanna@ligo.org
License: UNKNOWN
Platform: UNKNOWN
Classifier: Programming Language :: Python :: 3
Classifier: License :: OSI Approved :: GNU General Public License v2 or later (GPLv2+)
Classifier: Operating System :: OS Independent
Requires-Python: >=3.6
License-File: LICENSE
